geometric2dr/__init__.py
geometric2dr/data/__init__.py
geometric2dr/data/dortmund_formatter.py
geometric2dr/data/tu_gexifier.py
geometric2dr/decomposition/__init__.py
geometric2dr/decomposition/anonymous_walk_patterns.py
geometric2dr/decomposition/graphlet_patterns.py
geometric2dr/decomposition/random_walk_patterns.py
geometric2dr/decomposition/shortest_path_patterns.py
geometric2dr/decomposition/utils.py
geometric2dr/decomposition/weisfeiler_lehman_patterns.py
geometric2dr/decomposition/canonical_maps/canonical_map_n2.p
geometric2dr/decomposition/canonical_maps/canonical_map_n3.p
geometric2dr/decomposition/canonical_maps/canonical_map_n4.p
geometric2dr/decomposition/canonical_maps/canonical_map_n5.p
geometric2dr/decomposition/canonical_maps/canonical_map_n6.p
geometric2dr/decomposition/canonical_maps/canonical_map_n7.p
geometric2dr/decomposition/canonical_maps/canonical_map_n8.p
geometric2dr/decomposition/graphlet_counter_maps/graphlet_counter_nodebased_n2.p
geometric2dr/decomposition/graphlet_counter_maps/graphlet_counter_nodebased_n3.p
geometric2dr/decomposition/graphlet_counter_maps/graphlet_counter_nodebased_n4.p
geometric2dr/decomposition/graphlet_counter_maps/graphlet_counter_nodebased_n5.p
geometric2dr/decomposition/graphlet_counter_maps/graphlet_counter_nodebased_n6.p
geometric2dr/decomposition/graphlet_counter_maps/graphlet_counter_nodebased_n7.p
geometric2dr/decomposition/graphlet_counter_maps/graphlet_counter_nodebased_n8.p
geometric2dr/embedding_methods/__init__.py
geometric2dr/embedding_methods/cbow.py
geometric2dr/embedding_methods/cbow_data_reader.py
geometric2dr/embedding_methods/cbow_trainer.py
geometric2dr/embedding_methods/classify.py
geometric2dr/embedding_methods/dev_noclass_trainer.py
geometric2dr/embedding_methods/pvdbow_data_reader.py
geometric2dr/embedding_methods/pvdbow_trainer.py
geometric2dr/embedding_methods/pvdm.py
geometric2dr/embedding_methods/pvdm_data_reader.py
geometric2dr/embedding_methods/pvdm_trainer.py
geometric2dr-0.5.0.dist-info/LICENSE
geometric2dr-0.5.0.dist-info/METADATA
geometric2dr-0.5.0.dist-info/WHEEL
geometric2dr-0.5.0.dist-info/top_level.txt
geometric2dr-0.5.0.dist-info/RECORD
