Metadata-Version: 2.1
Name: geometric2dr
Version: 0.5.0
Summary: Geo2DR: Library to build distributed representations of graphs
Home-page: https://github.com/paulmorio/geo2dr
Author: Paul Scherer
Author-email: paul.geo2dr@gmail.com
License: MIT
Platform: UNKNOWN
Classifier: Topic :: Scientific/Engineering :: Artificial Intelligence
Classifier: License :: OSI Approved :: MIT License
Classifier: Natural Language :: English
Classifier: Programming Language :: Python :: 3.6
Classifier: Operating System :: OS Independent
Requires-Dist: numpy
Requires-Dist: scikit-learn
Requires-Dist: networkx
Requires-Dist: tqdm
Requires-Dist: ipython
Requires-Dist: torch
Requires-Dist: torchvision
